toml_validator/__init__.py
toml_validator/__main__.py
toml_validator/py.typed
toml_validator/use_cases/__init__.py
toml_validator/use_cases/toml.py
toml_validator-1.5.0.dist-info/entry_points.txt
toml_validator-1.5.0.dist-info/LICENSE.rst
toml_validator-1.5.0.dist-info/WHEEL
toml_validator-1.5.0.dist-info/METADATA
toml_validator-1.5.0.dist-info/RECORD
