Metadata-Version: 2.1
Name: toml-validator
Version: 1.5.0
Summary: Simple TOML file validator using Python.
Home-page: https://github.com/staticdev/toml-validator
License: MIT
Author: Thiago Carvalho D'Ávila
Author-email: thiagocavila@gmail.com
Requires-Python: >=3.7,<4.0
Classifier: License :: OSI Approved :: MIT License
Classifier: Programming Language :: Python :: 3
Classifier: Programming Language :: Python :: 3.7
Classifier: Programming Language :: Python :: 3.8
Requires-Dist: click (>=7.0,<8.0)
Requires-Dist: tomlkit (>=0.5.9,<0.8.0)
Project-URL: Changelog, https://github.com/staticdev/toml-validator/releases
Project-URL: Documentation, https://toml-validator.readthedocs.io
Project-URL: Repository, https://github.com/staticdev/toml-validator
